{
  "code": 0,
  "msg": "",
  "count": 1000,
  "data": [
    {
      "id": 3030173101,
      "username": "谭珍",
      "sex": "女",
      "city": "无锡",
      "sign": "21",
      "experience": 255,
      "logins": 24,
      "wealth": 1700,
      "classify": "学生",
      "class": "31731",
      "score": 57
    },
    {
      "id": 3030173102,
      "username": "寒冬",
      "sex": "男",
      "city": "徐州",
      "sign": "20",
      "experience": 884,
      "logins": 58,
      "wealth": 90,
      "classify": "学生",
      "class": "31732",
      "score": 27
    },
    {
      "id": 3030173103,
      "username": "李晶晶",
      "sex": "女",
      "city": "盐城",
      "sign": "21",
      "experience": 650,
      "logins": 77,
      "wealth": 78,
      "classify": "学生",
      "class": "31731",
      "score": 31
    },
    {
      "id": 3030173104,
      "username": "小迪",
      "sex": "女",
      "city": "山东",
      "sign": "21",
      "experience": 362,
      "logins": 157,
      "wealth": 17,
      "classify": "学生",
      "class": "31731",
      "score": 68
    },
    {
      "id": 3030173105,
      "username": "前程",
      "sex": "男",
      "city": "常州",
      "sign": "22",
      "experience": 807,
      "logins": 51,
      "wealth": 62,
      "classify": "学生",
      "class": "31731",
      "score": 6
    },
    {
      "id": 3030173106,
      "username": "黄时雨",
      "sex": "女",
      "city": "盐城",
      "sign": "21",
      "experience": 173,
      "logins": 68,
      "wealth": 47,
      "classify": "学生",
      "class": "31731",
      "score": 87
    },
    {
      "id": 3030173107,
      "username": "邹玲",
      "sex": "女",
      "city": "盐城",
      "sign": "21",
      "experience": 982,
      "logins": 37,
      "wealth": 66,
      "classify": "学生",
      "class": "31731",
      "score": 34
    },
    {
      "id": 3030173108,
      "username": "万里程",
      "sex": "男",
      "city": "武汉",
      "sign": "22",
      "experience": 727,
      "logins": 150,
      "wealth": 78,
      "classify": "学生",
      "class": "31731",
      "score": 28
    },
    {
      "id": 3030173109,
      "username": "郭浩峰",
      "sex": "男",
      "city": "四川",
      "sign": "22",
      "experience": 951,
      "logins": 133,
      "wealth": 71,
      "classify": "学生",
      "class": "31731",
      "score": 14
    },
    {
      "id": 3030173110,
      "username": "虞翠",
      "sex": "女",
      "city": "盐城",
      "sign": "21",
      "experience": 484,
      "logins": 25,
      "wealth": 34,
      "classify": "学生",
      "class": "31731",
      "score": 75
    }
  ]
}